fastapi_plus/__init__.py
fastapi_plus/config/__init__.py
fastapi_plus/config/anonymous.py
fastapi_plus/controller/__init__.py
fastapi_plus/controller/base.py
fastapi_plus/dao/__init__.py
fastapi_plus/dao/base.py
fastapi_plus/dao/event.py
fastapi_plus/model/__init__.py
fastapi_plus/model/base.py
fastapi_plus/model/event_log.py
fastapi_plus/schema/__init__.py
fastapi_plus/schema/base.py
fastapi_plus/service/__init__.py
fastapi_plus/service/base.py
fastapi_plus/service/sys_info.py
fastapi_plus/utils/__init__.py
fastapi_plus/utils/auth.py
fastapi_plus/utils/custom_route.py
fastapi_plus/utils/db.py
fastapi_plus/utils/json_custom.py
fastapi_plus/utils/json_encoders.py
fastapi_plus/utils/list2dict.py
fastapi_plus/utils/locker.py
fastapi_plus/utils/mongo.py
fastapi_plus/utils/obj2dict.py
fastapi_plus/utils/obj2json.py
fastapi_plus/utils/redis.py
fastapi_plus/utils/request_log.py
fastapi_plus/utils/sync_model.py
fastapi_plus/utils/wxapp.py
fastapi_plus-0.0.2.20200831.dist-info/LICENSE
fastapi_plus-0.0.2.20200831.dist-info/METADATA
fastapi_plus-0.0.2.20200831.dist-info/WHEEL
fastapi_plus-0.0.2.20200831.dist-info/top_level.txt
fastapi_plus-0.0.2.20200831.dist-info/RECORD
