Metadata-Version: 2.1
Name: fastapi-plus
Version: 0.0.2.20200831
Summary: This is a Python FastAPI project engineering library that includes tools and basic service classes.
Home-page: https://github.com/zhenqiang-sun/fastapi_plus
Author: Zhenqiang Sun
Author-email: zhenqiang.sun@gmail.com
License: UNKNOWN
Platform: UNKNOWN
Classifier: Programming Language :: Python :: 3
Classifier: License :: OSI Approved :: MIT License
Classifier: Operating System :: OS Independent
Requires-Python: >=3.6
Requires-Dist: fastapi (==0.61.1)
Requires-Dist: uvicorn (==0.11.8)
Requires-Dist: SQLAlchemy (==1.3.19)
Requires-Dist: PyMySQL (==0.10.0)
Requires-Dist: sqlacodegen (==2.3.0)
Requires-Dist: redis (==3.5.3)
Requires-Dist: pymongo (==3.11.0)
Requires-Dist: requests (==2.24.0)
Requires-Dist: python-multipart (==0.0.5)
Requires-Dist: aiofiles (==0.5.0)
